venakatest/__init__.py
venakatest/test.py
venakatest-0.1.36.dist-info/METADATA
venakatest-0.1.36.dist-info/WHEEL
venakatest-0.1.36.dist-info/entry_points.txt
venakatest-0.1.36.dist-info/top_level.txt
venakatest-0.1.36.dist-info/RECORD
